pybear_dask/__init__.py
pybear_dask/_version.py
pybear_dask/base/__init__.py
pybear_dask/base/_is_classifier.py
pybear_dask/model_selection/GSTCV/_GSTCVDask/GSTCVDask.py
pybear_dask/model_selection/GSTCV/_GSTCVDask/__init__.py
pybear_dask/model_selection/GSTCV/_GSTCVDask/_fit/__init__.py
pybear_dask/model_selection/GSTCV/_GSTCVDask/_fit/_estimator_fit_params_helper.py
pybear_dask/model_selection/GSTCV/_GSTCVDask/_fit/_fold_splitter.py
pybear_dask/model_selection/GSTCV/_GSTCVDask/_fit/_get_kfold.py
pybear_dask/model_selection/GSTCV/_GSTCVDask/_fit/_parallelized_fit.py
pybear_dask/model_selection/GSTCV/_GSTCVDask/_fit/_parallelized_scorer.py
pybear_dask/model_selection/GSTCV/_GSTCVDask/_fit/_parallelized_train_scorer.py
pybear_dask/model_selection/GSTCV/_GSTCVDask/_param_conditioning/__init__.py
pybear_dask/model_selection/GSTCV/_GSTCVDask/_param_conditioning/_scheduler.py
pybear_dask/model_selection/GSTCV/_GSTCVDask/_type_aliases.py
pybear_dask/model_selection/GSTCV/_GSTCVDask/_validation/__init__.py
pybear_dask/model_selection/GSTCV/_GSTCVDask/_validation/_cache_cv.py
pybear_dask/model_selection/GSTCV/_GSTCVDask/_validation/_dask_estimator.py
pybear_dask/model_selection/GSTCV/_GSTCVDask/_validation/_iid.py
pybear_dask/model_selection/GSTCV/_GSTCVDask/_validation/_validation.py
pybear_dask/model_selection/GSTCV/_GSTCVDask/_validation/_y.py
pybear_dask/model_selection/GSTCV/__init__.py
pybear_dask/model_selection/__init__.py
pybear_dask/model_selection/autogridsearch/AutoGSTCVDask.py
pybear_dask/model_selection/autogridsearch/AutoGridSearchCVDask.py
pybear_dask/model_selection/autogridsearch/__init__.py
pybear_dask/model_selection/autogridsearch/_autogridsearch_wrapper/__init__.py
pybear_dask/model_selection/autogridsearch/_autogridsearch_wrapper/_refit_can_be_skipped.py
pybear_dask-0.2.3.dist-info/METADATA
pybear_dask-0.2.3.dist-info/WHEEL
pybear_dask-0.2.3.dist-info/licenses/LICENSE
pybear_dask-0.2.3.dist-info/RECORD
