Metadata-Version: 2.4
Name: pybear-dask
Version: 0.2.3
Summary: Python modules for data analytics applications with dask
License: BSD-3-Clause
License-File: LICENSE
Keywords: python data analytics pybear dask
Author: Bill Sousa
Author-email: WKSJR99@msn.com
Maintainer: Bill Sousa
Requires-Python: >=3.10,<3.13
Classifier: License :: OSI Approved :: BSD License
Classifier: Programming Language :: Python :: 3
Classifier: Programming Language :: Python :: 3.10
Classifier: Programming Language :: Python :: 3.11
Classifier: Programming Language :: Python :: 3.12
Requires-Dist: dask (<2025.1)
Requires-Dist: dask-ml (<2025.1)
Requires-Dist: distributed (<2025.1)
Requires-Dist: pybear (>=0.2.0)
Requires-Dist: scikit-learn (<1.7)
Project-URL: Homepage, https://github.com/PylarBear/pybear-dask
Project-URL: Repository, https://github.com/PylarBear/pybear-dask
